cweqgen/__init__.py
cweqgen/_version.py
cweqgen/converters.py
cweqgen/definitions.py
cweqgen/equations.py
cweqgen/eqnfiles/brakingindex.yaml
cweqgen/eqnfiles/characteristicage.yaml
cweqgen/eqnfiles/ellipticityspindown.yaml
cweqgen/eqnfiles/gwluminosity.yaml
cweqgen/eqnfiles/h0.yaml
cweqgen/eqnfiles/h0spindown.yaml
cweqgen/eqnfiles/massquadrupole.yaml
cweqgen/eqnfiles/spindownluminosity.yaml
cweqgen/sphinx/__init__.py
cweqgen/sphinx/utils.py
cweqgen-0.4.4.dist-info/LICENSE
cweqgen-0.4.4.dist-info/METADATA
cweqgen-0.4.4.dist-info/WHEEL
cweqgen-0.4.4.dist-info/top_level.txt
cweqgen-0.4.4.dist-info/RECORD
